setup.py
copy2kindle/__init__.py
copy2kindle/cli.py
copy2kindle/common.py
copy2kindle/copier.py
copy2kindle/darwin.py
copy2kindle.egg-info/PKG-INFO
copy2kindle.egg-info/SOURCES.txt
copy2kindle.egg-info/dependency_links.txt
copy2kindle.egg-info/entry_points.txt
copy2kindle.egg-info/requires.txt
copy2kindle.egg-info/top_level.txt