Metadata-Version: 1.1
Name: copy2kindle
Version: 0.1
Summary: A tool to copy .mobi to USB-attached Kinlde
Home-page: https://github.com/dottedmag/copy2kindle
Author: Mikhail Gusarov
Author-email: dottedmag@dottedmag.net
License: BSD2
Keywords: kindle mobi ebook
Platform: UNKNOWN
Classifier: Development Status :: 3 - Alpha
Classifier: Environment :: Console
Classifier: Intended Audience :: End Users/Desktop
Classifier: License :: OSI Approved :: BSD License
Classifier: Operating System :: MacOS :: MacOS X
Classifier: Programming Language :: Python
Classifier: Topic :: Utilities
